{
  "title": "Istorie",
  "route": "/index.php/menu-1/menu-1x1/meniu-complex-fara-descriere-2/istorie",
  "breadcrumbs": [
    "Acasă",
    "Istorie"
  ],
  "contentHtml": "<div class=\"insidem\">\n                  <!-- component -->\n      \n<div class=\"news_item_a\">\n\t\t\n\t\t\n\t\n\t\t<div id=\"bt-zt\"><a href=\"http://i-realtor.org/\" target=\"_blank\" title=\"обзоры недвижимости\">обзоры недвижимости</a><br><a href=\"http://joomla-master.org/joomla-3.0.html/\" target=\"_blank\" title=\"лучшие шаблоны Joomla 3.0\">лучшие шаблоны Joomla 3.0</a></div>\t\t\n\t\n\t\n\t\n\t<div class=\"newsitem_text\">\n\t\t              \n\t\t        \n        \n\t\t<table border=\"0\" cellpadding=\"0\" cellspacing=\"4\">\n<tbody>\n<tr>\n<td>\n<p style=\"text-align: left;\"><span style=\"color: blue; font-size: xx-large;\" color=\"blue\" size=\"6\">&nbsp;&nbsp; Catedra de istorie</span></p>\n<br style=\"text-align: center;\"></td>\n</tr>\n<tr>\n<td>\n<table style=\"width: 597px; height: 73px;\" cellspacing=\"20\">\n<tbody>\n<tr>\n<td style=\"height: 120px; width: 120px;\" align=\"center\"><img src=\"http://www.cnnb.ro/alte/profesori/Pavel_Corina.JPG\" class=\"responsive-img\"></td>\n<td style=\"width: 270px;\"><span style=\"font-size: 12pt;\">prof. </span><i><span style=\"font-size: 12pt;\">Corina Roberta Pavel</span></i></td>\n<td></td>\n</tr>\n</tbody>\n</table>\n</td>\n</tr>\n<tr>\n<td>\n<table style=\"width: 600px; height: 73px;\" cellspacing=\"20\">\n<tbody>\n<tr>\n<td style=\"height: 120px; width: 120px;\" align=\"center\"><img src=\"http://www.cnnb.ro/alte/profesori/David_Alexandru.jpg\" class=\"responsive-img\"></td>\n<td style=\"width: 270px;\"><span style=\"font-size: 12pt;\">prof. dr. </span><i><span style=\"font-size: 12pt;\">Alexandru David</span></i></td>\n<td></td>\n</tr>\n</tbody>\n</table>\n</td>\n</tr>\n<tr>\n<td>\n<table style=\"width: 802px; height: 205px;\" cellspacing=\"20\">\n<tbody>\n<tr>\n<td style=\"height: 120px; width: 120px;\" align=\"center\"><img src=\"http://www.cnnb.ro/alte/profesori/fara_foto.JPG\" class=\"responsive-img\"></td>\n<td style=\"width: 400px;\"><span style=\"font-size: 12pt;\">prof.&nbsp;&nbsp;</span><i><span style=\"font-size: 12pt;\">Bădără-Neculai Adriana Claudia</span></i></td>\n<td></td>\n</tr>\n</tbody>\n</table>\n</td>\n</tr>\n</tbody>\n</table>\t\n\t\t</div>\n\t</div>\n<!--end news item -->\n<div id=\"bt-zt\"><a href=\"http://electrofans.net/\" target=\"_blank\" title=\"магазин музыкальных инструментов\">магазин музыкальных инструментов</a><br><a href=\"http://baby-market.org\" target=\"_blank\" title=\"купить детскую коляску\">купить детскую коляску</a></div>\n      <!-- end component -->\n            \t  <div class=\"clearm\"></div>\n    </div>\n    <!-- end mid block insidem class -->",
  "scrapedAt": "2026-05-22T01:10:29.377Z"
}
